{
  "title": "Can RoomPriceGenie provide accurate pricing for my vacation rentals?",
  "url": "https://roompricegenie.com/en_gb/can-roompricegenie-provide-accurate-pricing-for-my-properties/",
  "description": "Can RoomPriceGenie provide accurate pricing for my vacation rentals? The answer is a resounding yes. Let us show you how.",
  "content": "Each vacation rental tells its own story—whether it’s a cozy one-bedroom retreat overlooking the Mediterranean or a luxurious villa with private pools and sprawling terraces. With factors like location, facilities, and guest expectations varying widely, creating the right pricing strategy can seem impossible. That’s where RoomPriceGenie comes in. RoomPriceGenie understands the complexity of vacation rentals, offering an intuitive revenue management system that adapts to your unique needs. If you own vacation rentals, you might wonder: can RoomPriceGenie provide accurate, competitive pricing for my properties? The answer is a resoundingyes. Let us show you how. ## Dynamic Pricing Tailored to Every Vacation Rental Whether you have a handful of vacation rentals scattered along Cyprus’ stunning coastline or a portfolio of apartments in bustling cities, RoomPriceGenie is designed to handle the nuances of every property. The platform uses a powerful algorithm thatdynamically adjustsprices based on a variety of factors, including: - Market Intelligence: RoomPriceGenie analyzes real-time market trends, such as supply and demand shifts, competitor rates, and seasonal patterns. It ensures your vacation rentals remain competitively priced without missing out on revenue opportunities. - Booking Performance: The system optimizes pricing based on your current and projected occupancy, allowing you to attract bookings while maximizing revenue. - Demand Forecasts: RoomPriceGenie accounts for upcoming events, holidays, and market fluctuations, so you’re always one step ahead. With RoomPriceGenie, your pricing strategy isn’t just reactive—it’s proactive. By automatically adjusting rates based on market conditions, the platform ensures your vacation rentals stay attractive to guests while driving optimal revenue. ## Flexibility to Fit Your Unique Needs One of the standout features of RoomPriceGenie is its flexibility. We know that no two vacation rentals are alike, and the system reflects that understanding. Here’s how: - Custom Pricing Rules: Set minimum and maximum price thresholds for each property to ensure your rates align with your unique goals and costs. - Specific Adjustments: Apply custom pricing forspecial events, peak seasons, or even specific days of the week. For example, if a festival in Cyprus draws more visitors to your area, RoomPriceGenie will help you capitalize on the increased demand. - Vacation Rental Benchmarking: Gain valuable insights into how your properties perform against competitors in your destination. See shifts in supply and demand to fine-tune your strategy accordingly. - Transparency: There is no black box system but a transparent calculation of how we got to the right price, so you are always in control of your pricing. By adapting to the specific needs of your vacation rentals, RoomPriceGenie gives you complete control while saving you countless hours of manual pricing adjustments. ## Why Vacation Rentals Thrive with RoomPriceGenie Vacation rentals face unique challenges, from fluctuating demand to varying property features. RoomPriceGenie bridges the gap by offering a revenue management solution that combines: - Precision: Accurate pricing based on data-driven insights. - Transparency: Implement your strategy and adjust the algorithm to your needs, all while you still have full control and stay on top of what happens. - Ease: An intuitive system that saves you time while maximizing revenue. Natalia Assa, owner of Inn Your Element, said, “Accurate room pricing is crucial for success in today’s world. Since using RoomPriceGenie, our total revenue has increased considerably.” Read more of our customer’s success stories here → ## Watch Your Apartment’s Success Story with RoomPriceGenie Your Apartment started in 2017 as quite a small Airbnb management company. They have about 25 separate sites in Bristol in the United Kingdom, creating about 150 units. Before integrating RoomPriceGenie, the process was extremely exhausting and long-winded. “We have found that since implementing RoomPriceGenie, our revenue and occupancy have increased. I recommend RoomPriceGenie to other operators within the service apartment market and have 100% confidence in their product.” To learn how RoomPriceGenie can help your property increase your property’s profitability,start your free trialof our automated pricing solution today!",
  "category": "articles",
  "chunks": [
    "Each vacation rental tells its own story—whether it’s a cozy one-bedroom retreat overlooking the Mediterranean or a luxurious villa with private pools and sprawling terraces. With factors like location, facilities, and guest expectations varying widely, creating the right pricing strategy can seem impossible. That’s where RoomPriceGenie comes in. RoomPriceGenie understands the complexity of vacation rentals, offering an intuitive revenue management system that adapts to your unique needs. If you own vacation rentals, you might wonder: can RoomPriceGenie provide accurate, competitive pricing for my properties? The answer is a resoundingyes. Let us show you how. ## Dynamic Pricing Tailored to Every Vacation Rental Whether you have a handful of vacation rentals scattered along Cyprus’ stunning coastline or a portfolio of apartments in bustling cities, RoomPriceGenie is designed to handle the nuances of every property. The platform uses a powerful algorithm thatdynamically adjustsprices based on a variety of factors, including: - Market Intelligence: RoomPriceGenie analyzes real-time market trends, such as supply and demand shifts, competitor rates, and seasonal patterns. It ensures your vacation rentals remain competitively priced without missing out on revenue opportunities. - Booking Performance: The system optimizes pricing based on your current and projected occupancy, allowing you to attract bookings while maximizing revenue. - Demand Forecasts: RoomPriceGenie accounts for upcoming events, holidays, and market fluctuations, so you’re always one step ahead. With RoomPriceGenie, your pricing strategy isn’t just reactive—it’s proactive. By automatically adjusting rates based on market conditions, the platform ensures your vacation rentals stay attractive to guests while driving optimal revenue. ## Flexibility to Fit Your Unique Needs One of the standout features of RoomPriceGenie is its flexibility. We know that no two vacation rentals are alike, and the system reflects that understanding. Here’s how: - Custom Pricing Rules: Set minimum and maximum price thresholds for each property to ensure your rates align with your unique goals and costs. - Specific Adjustments: Apply custom pricing forspecial events, peak seasons, or even specific days of the week. For example, if a festival in Cyprus draws more visitors to your area, RoomPriceGenie will help you capitalize on the increased demand. - Vacation Rental Benchmarking: Gain valuable insights into how your properties perform against competitors in your destination. See shifts in supply and demand to fine-tune your strategy accordingly. - Transparency: There is no black box system but a transparent calculation of how we got to the right price, so you are always in control of your pricing. By adapting to the specific needs of your vacation rentals, RoomPriceGenie gives you complete control while saving you countless hours of manual pricing adjustments. ## Why Vacation Rentals Thrive with RoomPriceGenie Vacation rentals face unique challenges, from fluctuating demand to varying property features. RoomPriceGenie bridges the gap by offering a revenue management solution that combines: - Precision: Accurate pricing based on data-driven insights. - Transparency: Implement your strategy and adjust the algorithm to your needs, all while you still have full control and stay on top of what happens. - Ease: An intuitive system",
    "bridges the gap by offering a revenue management solution that combines: - Precision: Accurate pricing based on data-driven insights. - Transparency: Implement your strategy and adjust the algorithm to your needs, all while you still have full control and stay on top of what happens. - Ease: An intuitive system that saves you time while maximizing revenue. Natalia Assa, owner of Inn Your Element, said, “Accurate room pricing is crucial for success in today’s world. Since using RoomPriceGenie, our total revenue has increased considerably.” Read more of our customer’s success stories here → ## Watch Your Apartment’s Success Story with RoomPriceGenie Your Apartment started in 2017 as quite a small Airbnb management company. They have about 25 separate sites in Bristol in the United Kingdom, creating about 150 units. Before integrating RoomPriceGenie, the process was extremely exhausting and long-winded. “We have found that since implementing RoomPriceGenie, our revenue and occupancy have increased. I recommend RoomPriceGenie to other operators within the service apartment market and have 100% confidence in their product.” To learn how RoomPriceGenie can help your property increase your property’s profitability,start your free trialof our automated pricing solution today!"
  ]
}